pynter/__init__.py
pynter/pynter.py
pynter-0.1.6.dist-info/LICENSE
pynter-0.1.6.dist-info/METADATA
pynter-0.1.6.dist-info/WHEEL
pynter-0.1.6.dist-info/top_level.txt
pynter-0.1.6.dist-info/RECORD
